rmlb/__init__.py
rmlb-0.1.2.dist-info/entry_points.txt
rmlb-0.1.2.dist-info/LICENSE
rmlb-0.1.2.dist-info/WHEEL
rmlb-0.1.2.dist-info/METADATA
rmlb-0.1.2.dist-info/RECORD
